httpserver4u/__init__.py
httpserver4u/__main__.py
httpserver4u/server.py
httpserver4u-0.0.2.dist-info/LICENSE
httpserver4u-0.0.2.dist-info/METADATA
httpserver4u-0.0.2.dist-info/WHEEL
httpserver4u-0.0.2.dist-info/top_level.txt
httpserver4u-0.0.2.dist-info/RECORD
