Metadata-Version: 2.1
Name: httpserver4u
Version: 0.0.2
Summary: A simple HTTP server with file upload/download and quick text save function.
Author-email: Neko Null <jerrylu.ms@outlook.com>
Project-URL: Homepage, https://github.com/jerrylususu/simple_http_server_py/
Classifier: Programming Language :: Python :: 3
Classifier: License :: OSI Approved :: MIT License
Classifier: Operating System :: OS Independent
Requires-Python: >=3.6
License-File: LICENSE
